setup.py
Mocky.egg-info/PKG-INFO
Mocky.egg-info/SOURCES.txt
Mocky.egg-info/dependency_links.txt
Mocky.egg-info/entry_points.txt
Mocky.egg-info/not-zip-safe
Mocky.egg-info/top_level.txt
mocky/__init__.py
mocky/mocky.py
