Metadata-Version: 1.0
Name: Mocky
Version: 0.2
Summary: Mocky is a class that helps you create mock objects for use in doctests.
Home-page: http://cheeseshop.python.org/pypi/Mocky
Author: Daniel Nouri
Author-email: daniel.nouri@gmail.com
License: BSD
Keywords: test doctest mock
Platform: UNKNOWN
Classifier: Topic :: Software Development :: Testing
